folderclone/__init__.py
folderclone/_helpers.py
folderclone/multifolderclone.py
folderclone/multimanager.py
folderclonecli/__init__.py
folderclonecli/mfcparse.py
folderclonecli/mmparse.py
gdclone-0.5.5.dist-info/METADATA
gdclone-0.5.5.dist-info/WHEEL
gdclone-0.5.5.dist-info/entry_points.txt
gdclone-0.5.5.dist-info/top_level.txt
gdclone-0.5.5.dist-info/RECORD
