Metadata-Version: 2.1
Name: gdclone
Version: 0.5.5
Summary: A tool to copy large folders to Shared Drives.
Home-page: https://github.com/Spazzlo/folderclone
Author: Spazzlo
License: UNKNOWN
Platform: UNKNOWN
Classifier: Programming Language :: Python :: 3
Classifier: License :: OSI Approved :: MIT License
Classifier: Operating System :: OS Independent
Requires-Dist: google-auth-oauthlib
Requires-Dist: urllib3
Requires-Dist: httplib2shim
Requires-Dist: protobuf
Requires-Dist: pyreadline
Requires-Dist: google-api-python-client
